<?xml version="1.0" encoding="UTF-8"?>
<DEFECTS>
  <DEFECT>
    <SFA>
      <FILEPATH>G:\Compute Shader\framework\ext\</FILEPATH>
      <FILENAME>stb_image.h</FILENAME>
      <LINE>1048</LINE>
      <COLUMN>27</COLUMN>
    </SFA>
    <DEFECTCODE>26451</DEFECTCODE>
    <DESCRIPTION>Arithmetic overflow: Using operator '+' on a 4 byte value and then casting the result to a 8 byte value. Cast the value to the wider type before calling operator '+' to avoid overflow (io.2).</DESCRIPTION>
    <FUNCTION>stbi__malloc_mad2</FUNCTION>
    <DECORATED>?stbi__malloc_mad2@@YAPEAXHHH@Z</DECORATED>
    <FUNCLINE>1045</FUNCLINE>
    <PATH></PATH>
  </DEFECT>
  <DEFECT>
    <SFA>
      <FILEPATH>G:\Compute Shader\framework\ext\</FILEPATH>
      <FILENAME>stb_image.h</FILENAME>
      <LINE>1048</LINE>
      <COLUMN>24</COLUMN>
    </SFA>
    <DEFECTCODE>26451</DEFECTCODE>
    <DESCRIPTION>Arithmetic overflow: Using operator '*' on a 4 byte value and then casting the result to a 8 byte value. Cast the value to the wider type before calling operator '*' to avoid overflow (io.2).</DESCRIPTION>
    <FUNCTION>stbi__malloc_mad2</FUNCTION>
    <DECORATED>?stbi__malloc_mad2@@YAPEAXHHH@Z</DECORATED>
    <FUNCLINE>1045</FUNCLINE>
    <PATH></PATH>
  </DEFECT>
  <DEFECT>
    <SFA>
      <FILEPATH>G:\Compute Shader\framework\ext\</FILEPATH>
      <FILENAME>stb_image.h</FILENAME>
      <LINE>1055</LINE>
      <COLUMN>29</COLUMN>
    </SFA>
    <DEFECTCODE>26451</DEFECTCODE>
    <DESCRIPTION>Arithmetic overflow: Using operator '+' on a 4 byte value and then casting the result to a 8 byte value. Cast the value to the wider type before calling operator '+' to avoid overflow (io.2).</DESCRIPTION>
    <FUNCTION>stbi__malloc_mad3</FUNCTION>
    <DECORATED>?stbi__malloc_mad3@@YAPEAXHHHH@Z</DECORATED>
    <FUNCLINE>1052</FUNCLINE>
    <PATH></PATH>
  </DEFECT>
  <DEFECT>
    <SFA>
      <FILEPATH>G:\Compute Shader\framework\ext\</FILEPATH>
      <FILENAME>stb_image.h</FILENAME>
      <LINE>1055</LINE>
      <COLUMN>26</COLUMN>
    </SFA>
    <DEFECTCODE>26451</DEFECTCODE>
    <DESCRIPTION>Arithmetic overflow: Using operator '*' on a 4 byte value and then casting the result to a 8 byte value. Cast the value to the wider type before calling operator '*' to avoid overflow (io.2).</DESCRIPTION>
    <FUNCTION>stbi__malloc_mad3</FUNCTION>
    <DECORATED>?stbi__malloc_mad3@@YAPEAXHHHH@Z</DECORATED>
    <FUNCLINE>1052</FUNCLINE>
    <PATH></PATH>
  </DEFECT>
  <DEFECT>
    <SFA>
      <FILEPATH>G:\Compute Shader\framework\ext\</FILEPATH>
      <FILENAME>stb_image.h</FILENAME>
      <LINE>1055</LINE>
      <COLUMN>24</COLUMN>
    </SFA>
    <DEFECTCODE>26451</DEFECTCODE>
    <DESCRIPTION>Arithmetic overflow: Using operator '*' on a 4 byte value and then casting the result to a 8 byte value. Cast the value to the wider type before calling operator '*' to avoid overflow (io.2).</DESCRIPTION>
    <FUNCTION>stbi__malloc_mad3</FUNCTION>
    <DECORATED>?stbi__malloc_mad3@@YAPEAXHHHH@Z</DECORATED>
    <FUNCLINE>1052</FUNCLINE>
    <PATH></PATH>
  </DEFECT>
  <DEFECT>
    <SFA>
      <FILEPATH>G:\Compute Shader\framework\ext\</FILEPATH>
      <FILENAME>stb_image.h</FILENAME>
      <LINE>1062</LINE>
      <COLUMN>31</COLUMN>
    </SFA>
    <DEFECTCODE>26451</DEFECTCODE>
    <DESCRIPTION>Arithmetic overflow: Using operator '+' on a 4 byte value and then casting the result to a 8 byte value. Cast the value to the wider type before calling operator '+' to avoid overflow (io.2).</DESCRIPTION>
    <FUNCTION>stbi__malloc_mad4</FUNCTION>
    <DECORATED>?stbi__malloc_mad4@@YAPEAXHHHHH@Z</DECORATED>
    <FUNCLINE>1059</FUNCLINE>
    <PATH></PATH>
  </DEFECT>
  <DEFECT>
    <SFA>
      <FILEPATH>G:\Compute Shader\framework\ext\</FILEPATH>
      <FILENAME>stb_image.h</FILENAME>
      <LINE>1062</LINE>
      <COLUMN>28</COLUMN>
    </SFA>
    <DEFECTCODE>26451</DEFECTCODE>
    <DESCRIPTION>Arithmetic overflow: Using operator '*' on a 4 byte value and then casting the result to a 8 byte value. Cast the value to the wider type before calling operator '*' to avoid overflow (io.2).</DESCRIPTION>
    <FUNCTION>stbi__malloc_mad4</FUNCTION>
    <DECORATED>?stbi__malloc_mad4@@YAPEAXHHHHH@Z</DECORATED>
    <FUNCLINE>1059</FUNCLINE>
    <PATH></PATH>
  </DEFECT>
  <DEFECT>
    <SFA>
      <FILEPATH>G:\Compute Shader\framework\ext\</FILEPATH>
      <FILENAME>stb_image.h</FILENAME>
      <LINE>1062</LINE>
      <COLUMN>26</COLUMN>
    </SFA>
    <DEFECTCODE>26451</DEFECTCODE>
    <DESCRIPTION>Arithmetic overflow: Using operator '*' on a 4 byte value and then casting the result to a 8 byte value. Cast the value to the wider type before calling operator '*' to avoid overflow (io.2).</DESCRIPTION>
    <FUNCTION>stbi__malloc_mad4</FUNCTION>
    <DECORATED>?stbi__malloc_mad4@@YAPEAXHHHHH@Z</DECORATED>
    <FUNCLINE>1059</FUNCLINE>
    <PATH></PATH>
  </DEFECT>
  <DEFECT>
    <SFA>
      <FILEPATH>G:\Compute Shader\framework\ext\</FILEPATH>
      <FILENAME>stb_image.h</FILENAME>
      <LINE>1062</LINE>
      <COLUMN>24</COLUMN>
    </SFA>
    <DEFECTCODE>26451</DEFECTCODE>
    <DESCRIPTION>Arithmetic overflow: Using operator '*' on a 4 byte value and then casting the result to a 8 byte value. Cast the value to the wider type before calling operator '*' to avoid overflow (io.2).</DESCRIPTION>
    <FUNCTION>stbi__malloc_mad4</FUNCTION>
    <DECORATED>?stbi__malloc_mad4@@YAPEAXHHHHH@Z</DECORATED>
    <FUNCLINE>1059</FUNCLINE>
    <PATH></PATH>
  </DEFECT>
  <DEFECT>
    <SFA>
      <FILEPATH>G:\Compute Shader\framework\ext\</FILEPATH>
      <FILENAME>stb_image.h</FILENAME>
      <LINE>1192</LINE>
      <COLUMN>51</COLUMN>
    </SFA>
    <DEFECTCODE>26451</DEFECTCODE>
    <DESCRIPTION>Arithmetic overflow: Using operator '*' on a 4 byte value and then casting the result to a 8 byte value. Cast the value to the wider type before calling operator '*' to avoid overflow (io.2).</DESCRIPTION>
    <FUNCTION>stbi__convert_8_to_16</FUNCTION>
    <DECORATED>?stbi__convert_8_to_16@@YAPEAGPEAEHHH@Z</DECORATED>
    <FUNCLINE>1186</FUNCLINE>
    <PATH></PATH>
  </DEFECT>
  <DEFECT>
    <SFA>
      <FILEPATH>G:\Compute Shader\framework\ext\</FILEPATH>
      <FILENAME>stb_image.h</FILENAME>
      <LINE>1211</LINE>
      <COLUMN>39</COLUMN>
    </SFA>
    <DEFECTCODE>26451</DEFECTCODE>
    <DESCRIPTION>Arithmetic overflow: Using operator '-' on a 4 byte value and then casting the result to a 8 byte value. Cast the value to the wider type before calling operator '-' to avoid overflow (io.2).</DESCRIPTION>
    <FUNCTION>stbi__vertical_flip</FUNCTION>
    <DECORATED>?stbi__vertical_flip@@YAXPEAXHHH@Z</DECORATED>
    <FUNCLINE>1202</FUNCLINE>
    <PATH></PATH>
  </DEFECT>
  <DEFECT>
    <SFA>
      <FILEPATH>G:\Compute Shader\framework\ext\</FILEPATH>
      <FILENAME>stb_image.h</FILENAME>
      <LINE>1211</LINE>
      <COLUMN>33</COLUMN>
    </SFA>
    <DEFECTCODE>26451</DEFECTCODE>
    <DESCRIPTION>Arithmetic overflow: Using operator '-' on a 4 byte value and then casting the result to a 8 byte value. Cast the value to the wider type before calling operator '-' to avoid overflow (io.2).</DESCRIPTION>
    <FUNCTION>stbi__vertical_flip</FUNCTION>
    <DECORATED>?stbi__vertical_flip@@YAXPEAXHHH@Z</DECORATED>
    <FUNCLINE>1202</FUNCLINE>
    <PATH></PATH>
  </DEFECT>
  <DEFECT>
    <SFA>
      <FILEPATH>G:\Compute Shader\framework\ext\</FILEPATH>
      <FILENAME>stb_image.h</FILENAME>
      <LINE>1750</LINE>
      <COLUMN>41</COLUMN>
    </SFA>
    <DEFECTCODE>26451</DEFECTCODE>
    <DESCRIPTION>Arithmetic overflow: Using operator '*' on a 4 byte value and then casting the result to a 8 byte value. Cast the value to the wider type before calling operator '*' to avoid overflow (io.2).</DESCRIPTION>
    <FUNCTION>stbi__convert_format</FUNCTION>
    <DECORATED>?stbi__convert_format@@YAPEAEPEAEHHII@Z</DECORATED>
    <FUNCLINE>1735</FUNCLINE>
    <PATH></PATH>
  </DEFECT>
  <DEFECT>
    <SFA>
      <FILEPATH>G:\Compute Shader\framework\ext\</FILEPATH>
      <FILENAME>stb_image.h</FILENAME>
      <LINE>1750</LINE>
      <COLUMN>37</COLUMN>
    </SFA>
    <DEFECTCODE>26451</DEFECTCODE>
    <DESCRIPTION>Arithmetic overflow: Using operator '*' on a 4 byte value and then casting the result to a 8 byte value. Cast the value to the wider type before calling operator '*' to avoid overflow (io.2).</DESCRIPTION>
    <FUNCTION>stbi__convert_format</FUNCTION>
    <DECORATED>?stbi__convert_format@@YAPEAEPEAEHHII@Z</DECORATED>
    <FUNCLINE>1735</FUNCLINE>
    <PATH></PATH>
  </DEFECT>
  <DEFECT>
    <SFA>
      <FILEPATH>G:\Compute Shader\framework\ext\</FILEPATH>
      <FILENAME>stb_image.h</FILENAME>
      <LINE>1751</LINE>
      <COLUMN>41</COLUMN>
    </SFA>
    <DEFECTCODE>26451</DEFECTCODE>
    <DESCRIPTION>Arithmetic overflow: Using operator '*' on a 4 byte value and then casting the result to a 8 byte value. Cast the value to the wider type before calling operator '*' to avoid overflow (io.2).</DESCRIPTION>
    <FUNCTION>stbi__convert_format</FUNCTION>
    <DECORATED>?stbi__convert_format@@YAPEAEPEAEHHII@Z</DECORATED>
    <FUNCLINE>1735</FUNCLINE>
    <PATH></PATH>
  </DEFECT>
  <DEFECT>
    <SFA>
      <FILEPATH>G:\Compute Shader\framework\ext\</FILEPATH>
      <FILENAME>stb_image.h</FILENAME>
      <LINE>1751</LINE>
      <COLUMN>37</COLUMN>
    </SFA>
    <DEFECTCODE>26451</DEFECTCODE>
    <DESCRIPTION>Arithmetic overflow: Using operator '*' on a 4 byte value and then casting the result to a 8 byte value. Cast the value to the wider type before calling operator '*' to avoid overflow (io.2).</DESCRIPTION>
    <FUNCTION>stbi__convert_format</FUNCTION>
    <DECORATED>?stbi__convert_format@@YAPEAEPEAEHHII@Z</DECORATED>
    <FUNCLINE>1735</FUNCLINE>
    <PATH></PATH>
  </DEFECT>
  <DEFECT>
    <SFA>
      <FILEPATH>G:\Compute Shader\framework\ext\</FILEPATH>
      <FILENAME>stb_image.h</FILENAME>
      <LINE>1800</LINE>
      <COLUMN>57</COLUMN>
    </SFA>
    <DEFECTCODE>26451</DEFECTCODE>
    <DESCRIPTION>Arithmetic overflow: Using operator '*' on a 4 byte value and then casting the result to a 8 byte value. Cast the value to the wider type before calling operator '*' to avoid overflow (io.2).</DESCRIPTION>
    <FUNCTION>stbi__convert_format16</FUNCTION>
    <DECORATED>?stbi__convert_format16@@YAPEAGPEAGHHII@Z</DECORATED>
    <FUNCLINE>1792</FUNCLINE>
    <PATH></PATH>
  </DEFECT>
  <DEFECT>
    <SFA>
      <FILEPATH>G:\Compute Shader\framework\ext\</FILEPATH>
      <FILENAME>stb_image.h</FILENAME>
      <LINE>1800</LINE>
      <COLUMN>53</COLUMN>
    </SFA>
    <DEFECTCODE>26451</DEFECTCODE>
    <DESCRIPTION>Arithmetic overflow: Using operator '*' on a 4 byte value and then casting the result to a 8 byte value. Cast the value to the wider type before calling operator '*' to avoid overflow (io.2).</DESCRIPTION>
    <FUNCTION>stbi__convert_format16</FUNCTION>
    <DECORATED>?stbi__convert_format16@@YAPEAGPEAGHHII@Z</DECORATED>
    <FUNCLINE>1792</FUNCLINE>
    <PATH></PATH>
  </DEFECT>
  <DEFECT>
    <SFA>
      <FILEPATH>G:\Compute Shader\framework\ext\</FILEPATH>
      <FILENAME>stb_image.h</FILENAME>
      <LINE>1800</LINE>
      <COLUMN>49</COLUMN>
    </SFA>
    <DEFECTCODE>26451</DEFECTCODE>
    <DESCRIPTION>Arithmetic overflow: Using operator '*' on a 4 byte value and then casting the result to a 8 byte value. Cast the value to the wider type before calling operator '*' to avoid overflow (io.2).</DESCRIPTION>
    <FUNCTION>stbi__convert_format16</FUNCTION>
    <DECORATED>?stbi__convert_format16@@YAPEAGPEAGHHII@Z</DECORATED>
    <FUNCLINE>1792</FUNCLINE>
    <PATH></PATH>
  </DEFECT>
  <DEFECT>
    <SFA>
      <FILEPATH>G:\Compute Shader\framework\ext\</FILEPATH>
      <FILENAME>stb_image.h</FILENAME>
      <LINE>1807</LINE>
      <COLUMN>40</COLUMN>
    </SFA>
    <DEFECTCODE>26451</DEFECTCODE>
    <DESCRIPTION>Arithmetic overflow: Using operator '*' on a 4 byte value and then casting the result to a 8 byte value. Cast the value to the wider type before calling operator '*' to avoid overflow (io.2).</DESCRIPTION>
    <FUNCTION>stbi__convert_format16</FUNCTION>
    <DECORATED>?stbi__convert_format16@@YAPEAGPEAGHHII@Z</DECORATED>
    <FUNCLINE>1792</FUNCLINE>
    <PATH></PATH>
  </DEFECT>
  <DEFECT>
    <SFA>
      <FILEPATH>G:\Compute Shader\framework\ext\</FILEPATH>
      <FILENAME>stb_image.h</FILENAME>
      <LINE>1807</LINE>
      <COLUMN>36</COLUMN>
    </SFA>
    <DEFECTCODE>26451</DEFECTCODE>
    <DESCRIPTION>Arithmetic overflow: Using operator '*' on a 4 byte value and then casting the result to a 8 byte value. Cast the value to the wider type before calling operator '*' to avoid overflow (io.2).</DESCRIPTION>
    <FUNCTION>stbi__convert_format16</FUNCTION>
    <DECORATED>?stbi__convert_format16@@YAPEAGPEAGHHII@Z</DECORATED>
    <FUNCLINE>1792</FUNCLINE>
    <PATH></PATH>
  </DEFECT>
  <DEFECT>
    <SFA>
      <FILEPATH>G:\Compute Shader\framework\ext\</FILEPATH>
      <FILENAME>stb_image.h</FILENAME>
      <LINE>1808</LINE>
      <COLUMN>40</COLUMN>
    </SFA>
    <DEFECTCODE>26451</DEFECTCODE>
    <DESCRIPTION>Arithmetic overflow: Using operator '*' on a 4 byte value and then casting the result to a 8 byte value. Cast the value to the wider type before calling operator '*' to avoid overflow (io.2).</DESCRIPTION>
    <FUNCTION>stbi__convert_format16</FUNCTION>
    <DECORATED>?stbi__convert_format16@@YAPEAGPEAGHHII@Z</DECORATED>
    <FUNCLINE>1792</FUNCLINE>
    <PATH></PATH>
  </DEFECT>
  <DEFECT>
    <SFA>
      <FILEPATH>G:\Compute Shader\framework\ext\</FILEPATH>
      <FILENAME>stb_image.h</FILENAME>
      <LINE>1808</LINE>
      <COLUMN>36</COLUMN>
    </SFA>
    <DEFECTCODE>26451</DEFECTCODE>
    <DESCRIPTION>Arithmetic overflow: Using operator '*' on a 4 byte value and then casting the result to a 8 byte value. Cast the value to the wider type before calling operator '*' to avoid overflow (io.2).</DESCRIPTION>
    <FUNCTION>stbi__convert_format16</FUNCTION>
    <DECORATED>?stbi__convert_format16@@YAPEAGPEAGHHII@Z</DECORATED>
    <FUNCLINE>1792</FUNCLINE>
    <PATH></PATH>
  </DEFECT>
  <DEFECT>
    <SFA>
      <FILEPATH>G:\Compute Shader\framework\ext\</FILEPATH>
      <FILENAME>stb_image.h</FILENAME>
      <LINE>2988</LINE>
      <COLUMN>55</COLUMN>
    </SFA>
    <DEFECTCODE>26451</DEFECTCODE>
    <DESCRIPTION>Arithmetic overflow: Using operator '*' on a 4 byte value and then casting the result to a 8 byte value. Cast the value to the wider type before calling operator '*' to avoid overflow (io.2).</DESCRIPTION>
    <FUNCTION>stbi__parse_entropy_coded_data</FUNCTION>
    <DECORATED>?stbi__parse_entropy_coded_data@@YAHPEAUstbi__jpeg@@@Z</DECORATED>
    <FUNCLINE>2915</FUNCLINE>
    <PATH></PATH>
  </DEFECT>
  <DEFECT>
    <SFA>
      <FILEPATH>G:\Compute Shader\framework\ext\</FILEPATH>
      <FILENAME>stb_image.h</FILENAME>
      <LINE>3019</LINE>
      <COLUMN>64</COLUMN>
    </SFA>
    <DEFECTCODE>26451</DEFECTCODE>
    <DESCRIPTION>Arithmetic overflow: Using operator '*' on a 4 byte value and then casting the result to a 8 byte value. Cast the value to the wider type before calling operator '*' to avoid overflow (io.2).</DESCRIPTION>
    <FUNCTION>stbi__parse_entropy_coded_data</FUNCTION>
    <DECORATED>?stbi__parse_entropy_coded_data@@YAHPEAUstbi__jpeg@@@Z</DECORATED>
    <FUNCLINE>2915</FUNCLINE>
    <PATH></PATH>
  </DEFECT>
  <DEFECT>
    <SFA>
      <FILEPATH>G:\Compute Shader\framework\ext\</FILEPATH>
      <FILENAME>stb_image.h</FILENAME>
      <LINE>2933</LINE>
      <COLUMN>75</COLUMN>
    </SFA>
    <DEFECTCODE>26451</DEFECTCODE>
    <DESCRIPTION>Arithmetic overflow: Using operator '*' on a 4 byte value and then casting the result to a 8 byte value. Cast the value to the wider type before calling operator '*' to avoid overflow (io.2).</DESCRIPTION>
    <FUNCTION>stbi__parse_entropy_coded_data</FUNCTION>
    <DECORATED>?stbi__parse_entropy_coded_data@@YAHPEAUstbi__jpeg@@@Z</DECORATED>
    <FUNCLINE>2915</FUNCLINE>
    <PATH></PATH>
  </DEFECT>
  <DEFECT>
    <SFA>
      <FILEPATH>G:\Compute Shader\framework\ext\</FILEPATH>
      <FILENAME>stb_image.h</FILENAME>
      <LINE>2933</LINE>
      <COLUMN>73</COLUMN>
    </SFA>
    <DEFECTCODE>26451</DEFECTCODE>
    <DESCRIPTION>Arithmetic overflow: Using operator '*' on a 4 byte value and then casting the result to a 8 byte value. Cast the value to the wider type before calling operator '*' to avoid overflow (io.2).</DESCRIPTION>
    <FUNCTION>stbi__parse_entropy_coded_data</FUNCTION>
    <DECORATED>?stbi__parse_entropy_coded_data@@YAHPEAUstbi__jpeg@@@Z</DECORATED>
    <FUNCLINE>2915</FUNCLINE>
    <PATH></PATH>
  </DEFECT>
  <DEFECT>
    <SFA>
      <FILEPATH>G:\Compute Shader\framework\ext\</FILEPATH>
      <FILENAME>stb_image.h</FILENAME>
      <LINE>2933</LINE>
      <COLUMN>79</COLUMN>
    </SFA>
    <DEFECTCODE>26451</DEFECTCODE>
    <DESCRIPTION>Arithmetic overflow: Using operator '*' on a 4 byte value and then casting the result to a 8 byte value. Cast the value to the wider type before calling operator '*' to avoid overflow (io.2).</DESCRIPTION>
    <FUNCTION>stbi__parse_entropy_coded_data</FUNCTION>
    <DECORATED>?stbi__parse_entropy_coded_data@@YAHPEAUstbi__jpeg@@@Z</DECORATED>
    <FUNCLINE>2915</FUNCLINE>
    <PATH></PATH>
  </DEFECT>
  <DEFECT>
    <SFA>
      <FILEPATH>G:\Compute Shader\framework\ext\</FILEPATH>
      <FILENAME>stb_image.h</FILENAME>
      <LINE>2961</LINE>
      <COLUMN>82</COLUMN>
    </SFA>
    <DEFECTCODE>26451</DEFECTCODE>
    <DESCRIPTION>Arithmetic overflow: Using operator '*' on a 4 byte value and then casting the result to a 8 byte value. Cast the value to the wider type before calling operator '*' to avoid overflow (io.2).</DESCRIPTION>
    <FUNCTION>stbi__parse_entropy_coded_data</FUNCTION>
    <DECORATED>?stbi__parse_entropy_coded_data@@YAHPEAUstbi__jpeg@@@Z</DECORATED>
    <FUNCLINE>2915</FUNCLINE>
    <PATH></PATH>
  </DEFECT>
  <DEFECT>
    <SFA>
      <FILEPATH>G:\Compute Shader\framework\ext\</FILEPATH>
      <FILENAME>stb_image.h</FILENAME>
      <LINE>3056</LINE>
      <COLUMN>55</COLUMN>
    </SFA>
    <DEFECTCODE>26451</DEFECTCODE>
    <DESCRIPTION>Arithmetic overflow: Using operator '*' on a 4 byte value and then casting the result to a 8 byte value. Cast the value to the wider type before calling operator '*' to avoid overflow (io.2).</DESCRIPTION>
    <FUNCTION>stbi__jpeg_finish</FUNCTION>
    <DECORATED>?stbi__jpeg_finish@@YAXPEAUstbi__jpeg@@@Z</DECORATED>
    <FUNCLINE>3046</FUNCLINE>
    <PATH></PATH>
  </DEFECT>
  <DEFECT>
    <SFA>
      <FILEPATH>G:\Compute Shader\framework\ext\</FILEPATH>
      <FILENAME>stb_image.h</FILENAME>
      <LINE>3058</LINE>
      <COLUMN>75</COLUMN>
    </SFA>
    <DEFECTCODE>26451</DEFECTCODE>
    <DESCRIPTION>Arithmetic overflow: Using operator '*' on a 4 byte value and then casting the result to a 8 byte value. Cast the value to the wider type before calling operator '*' to avoid overflow (io.2).</DESCRIPTION>
    <FUNCTION>stbi__jpeg_finish</FUNCTION>
    <DECORATED>?stbi__jpeg_finish@@YAXPEAUstbi__jpeg@@@Z</DECORATED>
    <FUNCLINE>3046</FUNCLINE>
    <PATH></PATH>
  </DEFECT>
  <DEFECT>
    <SFA>
      <FILEPATH>G:\Compute Shader\framework\ext\</FILEPATH>
      <FILENAME>stb_image.h</FILENAME>
      <LINE>3058</LINE>
      <COLUMN>73</COLUMN>
    </SFA>
    <DEFECTCODE>26451</DEFECTCODE>
    <DESCRIPTION>Arithmetic overflow: Using operator '*' on a 4 byte value and then casting the result to a 8 byte value. Cast the value to the wider type before calling operator '*' to avoid overflow (io.2).</DESCRIPTION>
    <FUNCTION>stbi__jpeg_finish</FUNCTION>
    <DECORATED>?stbi__jpeg_finish@@YAXPEAUstbi__jpeg@@@Z</DECORATED>
    <FUNCLINE>3046</FUNCLINE>
    <PATH></PATH>
  </DEFECT>
  <DEFECT>
    <SFA>
      <FILEPATH>G:\Compute Shader\framework\ext\</FILEPATH>
      <FILENAME>stb_image.h</FILENAME>
      <LINE>3058</LINE>
      <COLUMN>79</COLUMN>
    </SFA>
    <DEFECTCODE>26451</DEFECTCODE>
    <DESCRIPTION>Arithmetic overflow: Using operator '*' on a 4 byte value and then casting the result to a 8 byte value. Cast the value to the wider type before calling operator '*' to avoid overflow (io.2).</DESCRIPTION>
    <FUNCTION>stbi__jpeg_finish</FUNCTION>
    <DECORATED>?stbi__jpeg_finish@@YAXPEAUstbi__jpeg@@@Z</DECORATED>
    <FUNCLINE>3046</FUNCLINE>
    <PATH></PATH>
  </DEFECT>
  <DEFECT>
    <SFA>
      <FILEPATH>G:\Compute Shader\framework\ext\</FILEPATH>
      <FILENAME>stb_image.h</FILENAME>
      <LINE>3534</LINE>
      <COLUMN>43</COLUMN>
    </SFA>
    <DEFECTCODE>26451</DEFECTCODE>
    <DESCRIPTION>Arithmetic overflow: Using operator '*' on a 4 byte value and then casting the result to a 8 byte value. Cast the value to the wider type before calling operator '*' to avoid overflow (io.2).</DESCRIPTION>
    <FUNCTION>stbi__resample_row_hv_2_simd</FUNCTION>
    <DECORATED>?stbi__resample_row_hv_2_simd@@YAPEAEPEAE00HH@Z</DECORATED>
    <FUNCLINE>3477</FUNCLINE>
    <PATH></PATH>
  </DEFECT>
  <DEFECT>
    <SFA>
      <FILEPATH>G:\Compute Shader\framework\ext\</FILEPATH>
      <FILENAME>stb_image.h</FILENAME>
      <LINE>3851</LINE>
      <COLUMN>71</COLUMN>
    </SFA>
    <DEFECTCODE>26451</DEFECTCODE>
    <DESCRIPTION>Arithmetic overflow: Using operator '+' on a 4 byte value and then casting the result to a 8 byte value. Cast the value to the wider type before calling operator '+' to avoid overflow (io.2).</DESCRIPTION>
    <FUNCTION>load_jpeg_image</FUNCTION>
    <DECORATED>?load_jpeg_image@@YAPEAEPEAUstbi__jpeg@@PEAH11H@Z</DECORATED>
    <FUNCLINE>3812</FUNCLINE>
    <PATH></PATH>
  </DEFECT>
  <DEFECT>
    <SFA>
      <FILEPATH>G:\Compute Shader\framework\ext\</FILEPATH>
      <FILENAME>stb_image.h</FILENAME>
      <LINE>3874</LINE>
      <COLUMN>49</COLUMN>
    </SFA>
    <DEFECTCODE>26451</DEFECTCODE>
    <DESCRIPTION>Arithmetic overflow: Using operator '*' on a 4 byte value and then casting the result to a 8 byte value. Cast the value to the wider type before calling operator '*' to avoid overflow (io.2).</DESCRIPTION>
    <FUNCTION>load_jpeg_image</FUNCTION>
    <DECORATED>?load_jpeg_image@@YAPEAEPEAUstbi__jpeg@@PEAH11H@Z</DECORATED>
    <FUNCLINE>3812</FUNCLINE>
    <PATH></PATH>
  </DEFECT>
  <DEFECT>
    <SFA>
      <FILEPATH>G:\Compute Shader\framework\ext\</FILEPATH>
      <FILENAME>stb_image.h</FILENAME>
      <LINE>3874</LINE>
      <COLUMN>35</COLUMN>
    </SFA>
    <DEFECTCODE>26451</DEFECTCODE>
    <DESCRIPTION>Arithmetic overflow: Using operator '*' on a 4 byte value and then casting the result to a 8 byte value. Cast the value to the wider type before calling operator '*' to avoid overflow (io.2).</DESCRIPTION>
    <FUNCTION>load_jpeg_image</FUNCTION>
    <DECORATED>?load_jpeg_image@@YAPEAEPEAUstbi__jpeg@@PEAH11H@Z</DECORATED>
    <FUNCLINE>3812</FUNCLINE>
    <PATH></PATH>
  </DEFECT>
  <DEFECT>
    <SFA>
      <FILEPATH>G:\Compute Shader\framework\ext\</FILEPATH>
      <FILENAME>stb_image.h</FILENAME>
      <LINE>4622</LINE>
      <COLUMN>36</COLUMN>
    </SFA>
    <DEFECTCODE>26451</DEFECTCODE>
    <DESCRIPTION>Arithmetic overflow: Using operator '*' on a 4 byte value and then casting the result to a 8 byte value. Cast the value to the wider type before calling operator '*' to avoid overflow (io.2).</DESCRIPTION>
    <FUNCTION>stbi__create_png_image_raw</FUNCTION>
    <DECORATED>?stbi__create_png_image_raw@@YAHPEAUstbi__png@@PEAEIHIIHH@Z</DECORATED>
    <FUNCLINE>4595</FUNCLINE>
    <PATH></PATH>
  </DEFECT>
  <DEFECT>
    <SFA>
      <FILEPATH>G:\Compute Shader\framework\ext\</FILEPATH>
      <FILENAME>stb_image.h</FILENAME>
      <LINE>4631</LINE>
      <COLUMN>17</COLUMN>
    </SFA>
    <DEFECTCODE>26451</DEFECTCODE>
    <DESCRIPTION>Arithmetic overflow: Using operator '*' on a 4 byte value and then casting the result to a 8 byte value. Cast the value to the wider type before calling operator '*' to avoid overflow (io.2).</DESCRIPTION>
    <FUNCTION>stbi__create_png_image_raw</FUNCTION>
    <DECORATED>?stbi__create_png_image_raw@@YAHPEAUstbi__png@@PEAEIHIIHH@Z</DECORATED>
    <FUNCLINE>4595</FUNCLINE>
    <PATH></PATH>
  </DEFECT>
  <DEFECT>
    <SFA>
      <FILEPATH>G:\Compute Shader\framework\ext\</FILEPATH>
      <FILENAME>stb_image.h</FILENAME>
      <LINE>4711</LINE>
      <COLUMN>33</COLUMN>
    </SFA>
    <DEFECTCODE>26451</DEFECTCODE>
    <DESCRIPTION>Arithmetic overflow: Using operator '*' on a 4 byte value and then casting the result to a 8 byte value. Cast the value to the wider type before calling operator '*' to avoid overflow (io.2).</DESCRIPTION>
    <FUNCTION>stbi__create_png_image_raw</FUNCTION>
    <DECORATED>?stbi__create_png_image_raw@@YAHPEAUstbi__png@@PEAEIHIIHH@Z</DECORATED>
    <FUNCLINE>4595</FUNCLINE>
    <PATH></PATH>
  </DEFECT>
  <DEFECT>
    <SFA>
      <FILEPATH>G:\Compute Shader\framework\ext\</FILEPATH>
      <FILENAME>stb_image.h</FILENAME>
      <LINE>4724</LINE>
      <COLUMN>39</COLUMN>
    </SFA>
    <DEFECTCODE>26451</DEFECTCODE>
    <DESCRIPTION>Arithmetic overflow: Using operator '*' on a 4 byte value and then casting the result to a 8 byte value. Cast the value to the wider type before calling operator '*' to avoid overflow (io.2).</DESCRIPTION>
    <FUNCTION>stbi__create_png_image_raw</FUNCTION>
    <DECORATED>?stbi__create_png_image_raw@@YAHPEAUstbi__png@@PEAEIHIIHH@Z</DECORATED>
    <FUNCLINE>4595</FUNCLINE>
    <PATH></PATH>
  </DEFECT>
  <DEFECT>
    <SFA>
      <FILEPATH>G:\Compute Shader\framework\ext\</FILEPATH>
      <FILENAME>stb_image.h</FILENAME>
      <LINE>4725</LINE>
      <COLUMN>39</COLUMN>
    </SFA>
    <DEFECTCODE>26451</DEFECTCODE>
    <DESCRIPTION>Arithmetic overflow: Using operator '*' on a 4 byte value and then casting the result to a 8 byte value. Cast the value to the wider type before calling operator '*' to avoid overflow (io.2).</DESCRIPTION>
    <FUNCTION>stbi__create_png_image_raw</FUNCTION>
    <DECORATED>?stbi__create_png_image_raw@@YAHPEAUstbi__png@@PEAEIHIIHH@Z</DECORATED>
    <FUNCLINE>4595</FUNCLINE>
    <PATH></PATH>
  </DEFECT>
  <DEFECT>
    <SFA>
      <FILEPATH>G:\Compute Shader\framework\ext\</FILEPATH>
      <FILENAME>stb_image.h</FILENAME>
      <LINE>4725</LINE>
      <COLUMN>45</COLUMN>
    </SFA>
    <DEFECTCODE>26451</DEFECTCODE>
    <DESCRIPTION>Arithmetic overflow: Using operator '*' on a 4 byte value and then casting the result to a 8 byte value. Cast the value to the wider type before calling operator '*' to avoid overflow (io.2).</DESCRIPTION>
    <FUNCTION>stbi__create_png_image_raw</FUNCTION>
    <DECORATED>?stbi__create_png_image_raw@@YAHPEAUstbi__png@@PEAEIHIIHH@Z</DECORATED>
    <FUNCLINE>4595</FUNCLINE>
    <PATH></PATH>
  </DEFECT>
  <DEFECT>
    <SFA>
      <FILEPATH>G:\Compute Shader\framework\ext\</FILEPATH>
      <FILENAME>stb_image.h</FILENAME>
      <LINE>4774</LINE>
      <COLUMN>33</COLUMN>
    </SFA>
    <DEFECTCODE>26451</DEFECTCODE>
    <DESCRIPTION>Arithmetic overflow: Using operator '*' on a 4 byte value and then casting the result to a 8 byte value. Cast the value to the wider type before calling operator '*' to avoid overflow (io.2).</DESCRIPTION>
    <FUNCTION>stbi__create_png_image_raw</FUNCTION>
    <DECORATED>?stbi__create_png_image_raw@@YAHPEAUstbi__png@@PEAEIHIIHH@Z</DECORATED>
    <FUNCLINE>4595</FUNCLINE>
    <PATH></PATH>
  </DEFECT>
  <DEFECT>
    <SFA>
      <FILEPATH>G:\Compute Shader\framework\ext\</FILEPATH>
      <FILENAME>stb_image.h</FILENAME>
      <LINE>4838</LINE>
      <COLUMN>47</COLUMN>
    </SFA>
    <DEFECTCODE>26451</DEFECTCODE>
    <DESCRIPTION>Arithmetic overflow: Using operator '*' on a 4 byte value and then casting the result to a 8 byte value. Cast the value to the wider type before calling operator '*' to avoid overflow (io.2).</DESCRIPTION>
    <FUNCTION>stbi__create_png_image</FUNCTION>
    <DECORATED>?stbi__create_png_image@@YAHPEAUstbi__png@@PEAEIHHHH@Z</DECORATED>
    <FUNCLINE>4807</FUNCLINE>
    <PATH></PATH>
  </DEFECT>
  <DEFECT>
    <SFA>
      <FILEPATH>G:\Compute Shader\framework\ext\</FILEPATH>
      <FILENAME>stb_image.h</FILENAME>
      <LINE>4838</LINE>
      <COLUMN>35</COLUMN>
    </SFA>
    <DEFECTCODE>26451</DEFECTCODE>
    <DESCRIPTION>Arithmetic overflow: Using operator '*' on a 4 byte value and then casting the result to a 8 byte value. Cast the value to the wider type before calling operator '*' to avoid overflow (io.2).</DESCRIPTION>
    <FUNCTION>stbi__create_png_image</FUNCTION>
    <DECORATED>?stbi__create_png_image@@YAHPEAUstbi__png@@PEAEIHHHH@Z</DECORATED>
    <FUNCLINE>4807</FUNCLINE>
    <PATH></PATH>
  </DEFECT>
  <DEFECT>
    <SFA>
      <FILEPATH>G:\Compute Shader\framework\ext\</FILEPATH>
      <FILENAME>stb_image.h</FILENAME>
      <LINE>4838</LINE>
      <COLUMN>65</COLUMN>
    </SFA>
    <DEFECTCODE>26451</DEFECTCODE>
    <DESCRIPTION>Arithmetic overflow: Using operator '*' on a 4 byte value and then casting the result to a 8 byte value. Cast the value to the wider type before calling operator '*' to avoid overflow (io.2).</DESCRIPTION>
    <FUNCTION>stbi__create_png_image</FUNCTION>
    <DECORATED>?stbi__create_png_image@@YAHPEAUstbi__png@@PEAEIHHHH@Z</DECORATED>
    <FUNCLINE>4807</FUNCLINE>
    <PATH></PATH>
  </DEFECT>
  <DEFECT>
    <SFA>
      <FILEPATH>G:\Compute Shader\framework\ext\</FILEPATH>
      <FILENAME>stb_image.h</FILENAME>
      <LINE>4839</LINE>
      <COLUMN>38</COLUMN>
    </SFA>
    <DEFECTCODE>26451</DEFECTCODE>
    <DESCRIPTION>Arithmetic overflow: Using operator '*' on a 4 byte value and then casting the result to a 8 byte value. Cast the value to the wider type before calling operator '*' to avoid overflow (io.2).</DESCRIPTION>
    <FUNCTION>stbi__create_png_image</FUNCTION>
    <DECORATED>?stbi__create_png_image@@YAHPEAUstbi__png@@PEAEIHHHH@Z</DECORATED>
    <FUNCLINE>4807</FUNCLINE>
    <PATH></PATH>
  </DEFECT>
  <DEFECT>
    <SFA>
      <FILEPATH>G:\Compute Shader\framework\ext\</FILEPATH>
      <FILENAME>stb_image.h</FILENAME>
      <LINE>4839</LINE>
      <COLUMN>35</COLUMN>
    </SFA>
    <DEFECTCODE>26451</DEFECTCODE>
    <DESCRIPTION>Arithmetic overflow: Using operator '+' on a 4 byte value and then casting the result to a 8 byte value. Cast the value to the wider type before calling operator '+' to avoid overflow (io.2).</DESCRIPTION>
    <FUNCTION>stbi__create_png_image</FUNCTION>
    <DECORATED>?stbi__create_png_image@@YAHPEAUstbi__png@@PEAEIHHHH@Z</DECORATED>
    <FUNCLINE>4807</FUNCLINE>
    <PATH></PATH>
  </DEFECT>
  <DEFECT>
    <SFA>
      <FILEPATH>G:\Compute Shader\framework\ext\</FILEPATH>
      <FILENAME>stb_image.h</FILENAME>
      <LINE>4839</LINE>
      <COLUMN>33</COLUMN>
    </SFA>
    <DEFECTCODE>26451</DEFECTCODE>
    <DESCRIPTION>Arithmetic overflow: Using operator '*' on a 4 byte value and then casting the result to a 8 byte value. Cast the value to the wider type before calling operator '*' to avoid overflow (io.2).</DESCRIPTION>
    <FUNCTION>stbi__create_png_image</FUNCTION>
    <DECORATED>?stbi__create_png_image@@YAHPEAUstbi__png@@PEAEIHHHH@Z</DECORATED>
    <FUNCLINE>4807</FUNCLINE>
    <PATH></PATH>
  </DEFECT>
  <DEFECT>
    <SFA>
      <FILEPATH>G:\Compute Shader\framework\ext\</FILEPATH>
      <FILENAME>stb_image.h</FILENAME>
      <LINE>5638</LINE>
      <COLUMN>49</COLUMN>
    </SFA>
    <DEFECTCODE>26451</DEFECTCODE>
    <DESCRIPTION>Arithmetic overflow: Using operator '*' on a 4 byte value and then casting the result to a 8 byte value. Cast the value to the wider type before calling operator '*' to avoid overflow (io.2).</DESCRIPTION>
    <FUNCTION>stbi__bmp_load</FUNCTION>
    <DECORATED>?stbi__bmp_load@@YAPEAXPEAUstbi__context@@PEAH11HPEAUstbi__result_info@@@Z</DECORATED>
    <FUNCLINE>5468</FUNCLINE>
    <PATH></PATH>
  </DEFECT>
  <DEFECT>
    <SFA>
      <FILEPATH>G:\Compute Shader\framework\ext\</FILEPATH>
      <FILENAME>stb_image.h</FILENAME>
      <LINE>5638</LINE>
      <COLUMN>40</COLUMN>
    </SFA>
    <DEFECTCODE>26451</DEFECTCODE>
    <DESCRIPTION>Arithmetic overflow: Using operator '*' on a 4 byte value and then casting the result to a 8 byte value. Cast the value to the wider type before calling operator '*' to avoid overflow (io.2).</DESCRIPTION>
    <FUNCTION>stbi__bmp_load</FUNCTION>
    <DECORATED>?stbi__bmp_load@@YAPEAXPEAUstbi__context@@PEAH11HPEAUstbi__result_info@@@Z</DECORATED>
    <FUNCLINE>5468</FUNCLINE>
    <PATH></PATH>
  </DEFECT>
  <DEFECT>
    <SFA>
      <FILEPATH>G:\Compute Shader\framework\ext\</FILEPATH>
      <FILENAME>stb_image.h</FILENAME>
      <LINE>5639</LINE>
      <COLUMN>52</COLUMN>
    </SFA>
    <DEFECTCODE>26451</DEFECTCODE>
    <DESCRIPTION>Arithmetic overflow: Using operator '*' on a 4 byte value and then casting the result to a 8 byte value. Cast the value to the wider type before calling operator '*' to avoid overflow (io.2).</DESCRIPTION>
    <FUNCTION>stbi__bmp_load</FUNCTION>
    <DECORATED>?stbi__bmp_load@@YAPEAXPEAUstbi__context@@PEAH11HPEAUstbi__result_info@@@Z</DECORATED>
    <FUNCLINE>5468</FUNCLINE>
    <PATH></PATH>
  </DEFECT>
  <DEFECT>
    <SFA>
      <FILEPATH>G:\Compute Shader\framework\ext\</FILEPATH>
      <FILENAME>stb_image.h</FILENAME>
      <LINE>5639</LINE>
      <COLUMN>43</COLUMN>
    </SFA>
    <DEFECTCODE>26451</DEFECTCODE>
    <DESCRIPTION>Arithmetic overflow: Using operator '*' on a 4 byte value and then casting the result to a 8 byte value. Cast the value to the wider type before calling operator '*' to avoid overflow (io.2).</DESCRIPTION>
    <FUNCTION>stbi__bmp_load</FUNCTION>
    <DECORATED>?stbi__bmp_load@@YAPEAXPEAUstbi__context@@PEAH11HPEAUstbi__result_info@@@Z</DECORATED>
    <FUNCLINE>5468</FUNCLINE>
    <PATH></PATH>
  </DEFECT>
  <DEFECT>
    <SFA>
      <FILEPATH>G:\Compute Shader\framework\ext\</FILEPATH>
      <FILENAME>stb_image.h</FILENAME>
      <LINE>5639</LINE>
      <COLUMN>40</COLUMN>
    </SFA>
    <DEFECTCODE>26451</DEFECTCODE>
    <DESCRIPTION>Arithmetic overflow: Using operator '-' on a 4 byte value and then casting the result to a 8 byte value. Cast the value to the wider type before calling operator '-' to avoid overflow (io.2).</DESCRIPTION>
    <FUNCTION>stbi__bmp_load</FUNCTION>
    <DECORATED>?stbi__bmp_load@@YAPEAXPEAUstbi__context@@PEAH11HPEAUstbi__result_info@@@Z</DECORATED>
    <FUNCLINE>5468</FUNCLINE>
    <PATH></PATH>
  </DEFECT>
  <DEFECT>
    <SFA>
      <FILEPATH>G:\Compute Shader\framework\ext\</FILEPATH>
      <FILENAME>stb_image.h</FILENAME>
      <LINE>5859</LINE>
      <COLUMN>52</COLUMN>
    </SFA>
    <DEFECTCODE>26451</DEFECTCODE>
    <DESCRIPTION>Arithmetic overflow: Using operator '*' on a 4 byte value and then casting the result to a 8 byte value. Cast the value to the wider type before calling operator '*' to avoid overflow (io.2).</DESCRIPTION>
    <FUNCTION>stbi__tga_load</FUNCTION>
    <DECORATED>?stbi__tga_load@@YAPEAXPEAUstbi__context@@PEAH11HPEAUstbi__result_info@@@Z</DECORATED>
    <FUNCLINE>5794</FUNCLINE>
    <PATH></PATH>
  </DEFECT>
  <DEFECT>
    <SFA>
      <FILEPATH>G:\Compute Shader\framework\ext\</FILEPATH>
      <FILENAME>stb_image.h</FILENAME>
      <LINE>5859</LINE>
      <COLUMN>42</COLUMN>
    </SFA>
    <DEFECTCODE>26451</DEFECTCODE>
    <DESCRIPTION>Arithmetic overflow: Using operator '*' on a 4 byte value and then casting the result to a 8 byte value. Cast the value to the wider type before calling operator '*' to avoid overflow (io.2).</DESCRIPTION>
    <FUNCTION>stbi__tga_load</FUNCTION>
    <DECORATED>?stbi__tga_load@@YAPEAXPEAUstbi__context@@PEAH11HPEAUstbi__result_info@@@Z</DECORATED>
    <FUNCLINE>5794</FUNCLINE>
    <PATH></PATH>
  </DEFECT>
  <DEFECT>
    <SFA>
      <FILEPATH>G:\Compute Shader\framework\ext\</FILEPATH>
      <FILENAME>stb_image.h</FILENAME>
      <LINE>6127</LINE>
      <COLUMN>42</COLUMN>
    </SFA>
    <DEFECTCODE>26451</DEFECTCODE>
    <DESCRIPTION>Arithmetic overflow: Using operator '*' on a 4 byte value and then casting the result to a 8 byte value. Cast the value to the wider type before calling operator '*' to avoid overflow (io.2).</DESCRIPTION>
    <FUNCTION>stbi__psd_load</FUNCTION>
    <DECORATED>?stbi__psd_load@@YAPEAXPEAUstbi__context@@PEAH11HPEAUstbi__result_info@@H@Z</DECORATED>
    <FUNCLINE>6049</FUNCLINE>
    <PATH></PATH>
  </DEFECT>
  <DEFECT>
    <SFA>
      <FILEPATH>G:\Compute Shader\framework\ext\</FILEPATH>
      <FILENAME>stb_image.h</FILENAME>
      <LINE>6127</LINE>
      <COLUMN>39</COLUMN>
    </SFA>
    <DEFECTCODE>26451</DEFECTCODE>
    <DESCRIPTION>Arithmetic overflow: Using operator '*' on a 4 byte value and then casting the result to a 8 byte value. Cast the value to the wider type before calling operator '*' to avoid overflow (io.2).</DESCRIPTION>
    <FUNCTION>stbi__psd_load</FUNCTION>
    <DECORATED>?stbi__psd_load@@YAPEAXPEAUstbi__context@@PEAH11HPEAUstbi__result_info@@H@Z</DECORATED>
    <FUNCLINE>6049</FUNCLINE>
    <PATH></PATH>
  </DEFECT>
  <DEFECT>
    <SFA>
      <FILEPATH>G:\Compute Shader\framework\ext\</FILEPATH>
      <FILENAME>stb_image.h</FILENAME>
      <LINE>6209</LINE>
      <COLUMN>58</COLUMN>
    </SFA>
    <DEFECTCODE>26451</DEFECTCODE>
    <DESCRIPTION>Arithmetic overflow: Using operator '*' on a 4 byte value and then casting the result to a 8 byte value. Cast the value to the wider type before calling operator '*' to avoid overflow (io.2).</DESCRIPTION>
    <FUNCTION>stbi__psd_load</FUNCTION>
    <DECORATED>?stbi__psd_load@@YAPEAXPEAUstbi__context@@PEAH11HPEAUstbi__result_info@@H@Z</DECORATED>
    <FUNCLINE>6049</FUNCLINE>
    <PATH></PATH>
  </DEFECT>
  <DEFECT>
    <SFA>
      <FILEPATH>G:\Compute Shader\framework\ext\</FILEPATH>
      <FILENAME>stb_image.h</FILENAME>
      <LINE>6221</LINE>
      <COLUMN>42</COLUMN>
    </SFA>
    <DEFECTCODE>26451</DEFECTCODE>
    <DESCRIPTION>Arithmetic overflow: Using operator '*' on a 4 byte value and then casting the result to a 8 byte value. Cast the value to the wider type before calling operator '*' to avoid overflow (io.2).</DESCRIPTION>
    <FUNCTION>stbi__psd_load</FUNCTION>
    <DECORATED>?stbi__psd_load@@YAPEAXPEAUstbi__context@@PEAH11HPEAUstbi__result_info@@H@Z</DECORATED>
    <FUNCLINE>6049</FUNCLINE>
    <PATH></PATH>
  </DEFECT>
  <DEFECT>
    <SFA>
      <FILEPATH>G:\Compute Shader\framework\ext\</FILEPATH>
      <FILENAME>stb_image.h</FILENAME>
      <LINE>6346</LINE>
      <COLUMN>39</COLUMN>
    </SFA>
    <DEFECTCODE>26451</DEFECTCODE>
    <DESCRIPTION>Arithmetic overflow: Using operator '*' on a 4 byte value and then casting the result to a 8 byte value. Cast the value to the wider type before calling operator '*' to avoid overflow (io.2).</DESCRIPTION>
    <FUNCTION>stbi__pic_load_core</FUNCTION>
    <DECORATED>?stbi__pic_load_core@@YAPEAEPEAUstbi__context@@HHPEAHPEAE@Z</DECORATED>
    <FUNCLINE>6313</FUNCLINE>
    <PATH></PATH>
  </DEFECT>
  <DEFECT>
    <SFA>
      <FILEPATH>G:\Compute Shader\framework\ext\</FILEPATH>
      <FILENAME>stb_image.h</FILENAME>
      <LINE>6346</LINE>
      <COLUMN>33</COLUMN>
    </SFA>
    <DEFECTCODE>26451</DEFECTCODE>
    <DESCRIPTION>Arithmetic overflow: Using operator '*' on a 4 byte value and then casting the result to a 8 byte value. Cast the value to the wider type before calling operator '*' to avoid overflow (io.2).</DESCRIPTION>
    <FUNCTION>stbi__pic_load_core</FUNCTION>
    <DECORATED>?stbi__pic_load_core@@YAPEAEPEAUstbi__context@@HHPEAHPEAE@Z</DECORATED>
    <FUNCLINE>6313</FUNCLINE>
    <PATH></PATH>
  </DEFECT>
  <DEFECT>
    <SFA>
      <FILEPATH>G:\Compute Shader\framework\ext\</FILEPATH>
      <FILENAME>stb_image.h</FILENAME>
      <LINE>6450</LINE>
      <COLUMN>27</COLUMN>
    </SFA>
    <DEFECTCODE>26451</DEFECTCODE>
    <DESCRIPTION>Arithmetic overflow: Using operator '*' on a 4 byte value and then casting the result to a 8 byte value. Cast the value to the wider type before calling operator '*' to avoid overflow (io.2).</DESCRIPTION>
    <FUNCTION>stbi__pic_load</FUNCTION>
    <DECORATED>?stbi__pic_load@@YAPEAXPEAUstbi__context@@PEAH11HPEAUstbi__result_info@@@Z</DECORATED>
    <FUNCLINE>6423</FUNCLINE>
    <PATH></PATH>
  </DEFECT>
  <DEFECT>
    <SFA>
      <FILEPATH>G:\Compute Shader\framework\ext\</FILEPATH>
      <FILENAME>stb_image.h</FILENAME>
      <LINE>6450</LINE>
      <COLUMN>25</COLUMN>
    </SFA>
    <DEFECTCODE>26451</DEFECTCODE>
    <DESCRIPTION>Arithmetic overflow: Using operator '*' on a 4 byte value and then casting the result to a 8 byte value. Cast the value to the wider type before calling operator '*' to avoid overflow (io.2).</DESCRIPTION>
    <FUNCTION>stbi__pic_load</FUNCTION>
    <DECORATED>?stbi__pic_load@@YAPEAXPEAUstbi__context@@PEAH11HPEAUstbi__result_info@@@Z</DECORATED>
    <FUNCLINE>6423</FUNCLINE>
    <PATH></PATH>
  </DEFECT>
  <DEFECT>
    <SFA>
      <FILEPATH>G:\Compute Shader\framework\ext\</FILEPATH>
      <FILENAME>stb_image.h</FILENAME>
      <LINE>6716</LINE>
      <COLUMN>42</COLUMN>
    </SFA>
    <DEFECTCODE>26451</DEFECTCODE>
    <DESCRIPTION>Arithmetic overflow: Using operator '*' on a 4 byte value and then casting the result to a 8 byte value. Cast the value to the wider type before calling operator '*' to avoid overflow (io.2).</DESCRIPTION>
    <FUNCTION>stbi__gif_load_next</FUNCTION>
    <DECORATED>?stbi__gif_load_next@@YAPEAEPEAUstbi__context@@PEAUstbi__gif@@PEAHHPEAE@Z</DECORATED>
    <FUNCLINE>6701</FUNCLINE>
    <PATH></PATH>
  </DEFECT>
  <DEFECT>
    <SFA>
      <FILEPATH>G:\Compute Shader\framework\ext\</FILEPATH>
      <FILENAME>stb_image.h</FILENAME>
      <LINE>6717</LINE>
      <COLUMN>49</COLUMN>
    </SFA>
    <DEFECTCODE>26451</DEFECTCODE>
    <DESCRIPTION>Arithmetic overflow: Using operator '*' on a 4 byte value and then casting the result to a 8 byte value. Cast the value to the wider type before calling operator '*' to avoid overflow (io.2).</DESCRIPTION>
    <FUNCTION>stbi__gif_load_next</FUNCTION>
    <DECORATED>?stbi__gif_load_next@@YAPEAEPEAUstbi__context@@PEAUstbi__gif@@PEAHHPEAE@Z</DECORATED>
    <FUNCLINE>6701</FUNCLINE>
    <PATH></PATH>
  </DEFECT>
  <DEFECT>
    <SFA>
      <FILEPATH>G:\Compute Shader\framework\ext\</FILEPATH>
      <FILENAME>stb_image.h</FILENAME>
      <LINE>6725</LINE>
      <COLUMN>29</COLUMN>
    </SFA>
    <DEFECTCODE>26451</DEFECTCODE>
    <DESCRIPTION>Arithmetic overflow: Using operator '*' on a 4 byte value and then casting the result to a 8 byte value. Cast the value to the wider type before calling operator '*' to avoid overflow (io.2).</DESCRIPTION>
    <FUNCTION>stbi__gif_load_next</FUNCTION>
    <DECORATED>?stbi__gif_load_next@@YAPEAEPEAUstbi__context@@PEAUstbi__gif@@PEAHHPEAE@Z</DECORATED>
    <FUNCLINE>6701</FUNCLINE>
    <PATH></PATH>
  </DEFECT>
  <DEFECT>
    <SFA>
      <FILEPATH>G:\Compute Shader\framework\ext\</FILEPATH>
      <FILENAME>stb_image.h</FILENAME>
      <LINE>6726</LINE>
      <COLUMN>36</COLUMN>
    </SFA>
    <DEFECTCODE>26451</DEFECTCODE>
    <DESCRIPTION>Arithmetic overflow: Using operator '*' on a 4 byte value and then casting the result to a 8 byte value. Cast the value to the wider type before calling operator '*' to avoid overflow (io.2).</DESCRIPTION>
    <FUNCTION>stbi__gif_load_next</FUNCTION>
    <DECORATED>?stbi__gif_load_next@@YAPEAEPEAUstbi__context@@PEAUstbi__gif@@PEAHHPEAE@Z</DECORATED>
    <FUNCLINE>6701</FUNCLINE>
    <PATH></PATH>
  </DEFECT>
  <DEFECT>
    <SFA>
      <FILEPATH>G:\Compute Shader\framework\ext\</FILEPATH>
      <FILENAME>stb_image.h</FILENAME>
      <LINE>6759</LINE>
      <COLUMN>46</COLUMN>
    </SFA>
    <DEFECTCODE>26451</DEFECTCODE>
    <DESCRIPTION>Arithmetic overflow: Using operator '*' on a 4 byte value and then casting the result to a 8 byte value. Cast the value to the wider type before calling operator '*' to avoid overflow (io.2).</DESCRIPTION>
    <FUNCTION>stbi__gif_load_next</FUNCTION>
    <DECORATED>?stbi__gif_load_next@@YAPEAEPEAUstbi__context@@PEAUstbi__gif@@PEAHHPEAE@Z</DECORATED>
    <FUNCLINE>6701</FUNCLINE>
    <PATH></PATH>
  </DEFECT>
  <DEFECT>
    <SFA>
      <FILEPATH>G:\Compute Shader\framework\ext\</FILEPATH>
      <FILENAME>stb_image.h</FILENAME>
      <LINE>6759</LINE>
      <COLUMN>39</COLUMN>
    </SFA>
    <DEFECTCODE>26451</DEFECTCODE>
    <DESCRIPTION>Arithmetic overflow: Using operator '*' on a 4 byte value and then casting the result to a 8 byte value. Cast the value to the wider type before calling operator '*' to avoid overflow (io.2).</DESCRIPTION>
    <FUNCTION>stbi__gif_load_next</FUNCTION>
    <DECORATED>?stbi__gif_load_next@@YAPEAEPEAUstbi__context@@PEAUstbi__gif@@PEAHHPEAE@Z</DECORATED>
    <FUNCLINE>6701</FUNCLINE>
    <PATH></PATH>
  </DEFECT>
  <DEFECT>
    <SFA>
      <FILEPATH>G:\Compute Shader\framework\ext\</FILEPATH>
      <FILENAME>stb_image.h</FILENAME>
      <LINE>6763</LINE>
      <COLUMN>34</COLUMN>
    </SFA>
    <DEFECTCODE>26451</DEFECTCODE>
    <DESCRIPTION>Arithmetic overflow: Using operator '*' on a 4 byte value and then casting the result to a 8 byte value. Cast the value to the wider type before calling operator '*' to avoid overflow (io.2).</DESCRIPTION>
    <FUNCTION>stbi__gif_load_next</FUNCTION>
    <DECORATED>?stbi__gif_load_next@@YAPEAEPEAUstbi__context@@PEAUstbi__gif@@PEAHHPEAE@Z</DECORATED>
    <FUNCLINE>6701</FUNCLINE>
    <PATH></PATH>
  </DEFECT>
  <DEFECT>
    <SFA>
      <FILEPATH>G:\Compute Shader\framework\ext\</FILEPATH>
      <FILENAME>stb_image.h</FILENAME>
      <LINE>6886</LINE>
      <COLUMN>13</COLUMN>
    </SFA>
    <DEFECTCODE>6262</DEFECTCODE>
    <DESCRIPTION>Function uses '35036' bytes of stack.  Consider moving some data to heap.</DESCRIPTION>
    <FUNCTION>stbi__load_gif_main</FUNCTION>
    <DECORATED>?stbi__load_gif_main@@YAPEAXPEAUstbi__context@@PEAPEAHPEAH222H@Z</DECORATED>
    <FUNCLINE>6886</FUNCLINE>
    <PATH></PATH>
  </DEFECT>
  <DEFECT>
    <SFA>
      <FILEPATH>G:\Compute Shader\framework\ext\</FILEPATH>
      <FILENAME>stb_image.h</FILENAME>
      <LINE>6917</LINE>
      <COLUMN>38</COLUMN>
    </SFA>
    <DEFECTCODE>26451</DEFECTCODE>
    <DESCRIPTION>Arithmetic overflow: Using operator '*' on a 4 byte value and then casting the result to a 8 byte value. Cast the value to the wider type before calling operator '*' to avoid overflow (io.2).</DESCRIPTION>
    <FUNCTION>stbi__load_gif_main</FUNCTION>
    <DECORATED>?stbi__load_gif_main@@YAPEAXPEAUstbi__context@@PEAPEAHPEAH222H@Z</DECORATED>
    <FUNCLINE>6886</FUNCLINE>
    <PATH></PATH>
  </DEFECT>
  <DEFECT>
    <SFA>
      <FILEPATH>G:\Compute Shader\framework\ext\</FILEPATH>
      <FILENAME>stb_image.h</FILENAME>
      <LINE>6933</LINE>
      <COLUMN>52</COLUMN>
    </SFA>
    <DEFECTCODE>26451</DEFECTCODE>
    <DESCRIPTION>Arithmetic overflow: Using operator '*' on a 4 byte value and then casting the result to a 8 byte value. Cast the value to the wider type before calling operator '*' to avoid overflow (io.2).</DESCRIPTION>
    <FUNCTION>stbi__load_gif_main</FUNCTION>
    <DECORATED>?stbi__load_gif_main@@YAPEAXPEAUstbi__context@@PEAPEAHPEAH222H@Z</DECORATED>
    <FUNCLINE>6886</FUNCLINE>
    <PATH></PATH>
  </DEFECT>
  <DEFECT>
    <SFA>
      <FILEPATH>G:\Compute Shader\framework\ext\</FILEPATH>
      <FILENAME>stb_image.h</FILENAME>
      <LINE>6944</LINE>
      <COLUMN>40</COLUMN>
    </SFA>
    <DEFECTCODE>26451</DEFECTCODE>
    <DESCRIPTION>Arithmetic overflow: Using operator '*' on a 4 byte value and then casting the result to a 8 byte value. Cast the value to the wider type before calling operator '*' to avoid overflow (io.2).</DESCRIPTION>
    <FUNCTION>stbi__load_gif_main</FUNCTION>
    <DECORATED>?stbi__load_gif_main@@YAPEAXPEAUstbi__context@@PEAPEAHPEAH222H@Z</DECORATED>
    <FUNCLINE>6886</FUNCLINE>
    <PATH></PATH>
  </DEFECT>
  <DEFECT>
    <SFA>
      <FILEPATH>G:\Compute Shader\framework\ext\</FILEPATH>
      <FILENAME>stb_image.h</FILENAME>
      <LINE>6944</LINE>
      <COLUMN>35</COLUMN>
    </SFA>
    <DEFECTCODE>26451</DEFECTCODE>
    <DESCRIPTION>Arithmetic overflow: Using operator '-' on a 4 byte value and then casting the result to a 8 byte value. Cast the value to the wider type before calling operator '-' to avoid overflow (io.2).</DESCRIPTION>
    <FUNCTION>stbi__load_gif_main</FUNCTION>
    <DECORATED>?stbi__load_gif_main@@YAPEAXPEAUstbi__context@@PEAPEAHPEAH222H@Z</DECORATED>
    <FUNCLINE>6886</FUNCLINE>
    <PATH></PATH>
  </DEFECT>
  <DEFECT>
    <SFA>
      <FILEPATH>G:\Compute Shader\framework\ext\</FILEPATH>
      <FILENAME>stb_image.h</FILENAME>
      <LINE>6946</LINE>
      <COLUMN>34</COLUMN>
    </SFA>
    <DEFECTCODE>26451</DEFECTCODE>
    <DESCRIPTION>Arithmetic overflow: Using operator '*' on a 4 byte value and then casting the result to a 8 byte value. Cast the value to the wider type before calling operator '*' to avoid overflow (io.2).</DESCRIPTION>
    <FUNCTION>stbi__load_gif_main</FUNCTION>
    <DECORATED>?stbi__load_gif_main@@YAPEAXPEAUstbi__context@@PEAPEAHPEAH222H@Z</DECORATED>
    <FUNCLINE>6886</FUNCLINE>
    <PATH></PATH>
  </DEFECT>
  <DEFECT>
    <SFA>
      <FILEPATH>G:\Compute Shader\framework\ext\</FILEPATH>
      <FILENAME>stb_image.h</FILENAME>
      <LINE>6971</LINE>
      <COLUMN>13</COLUMN>
    </SFA>
    <DEFECTCODE>6262</DEFECTCODE>
    <DESCRIPTION>Function uses '34980' bytes of stack.  Consider moving some data to heap.</DESCRIPTION>
    <FUNCTION>stbi__gif_load</FUNCTION>
    <DECORATED>?stbi__gif_load@@YAPEAXPEAUstbi__context@@PEAH11HPEAUstbi__result_info@@@Z</DECORATED>
    <FUNCLINE>6971</FUNCLINE>
    <PATH></PATH>
  </DEFECT>
  <DEFECT>
    <SFA>
      <FILEPATH>G:\Compute Shader\framework\ext\</FILEPATH>
      <FILENAME>stb_image.h</FILENAME>
      <LINE>7146</LINE>
      <COLUMN>51</COLUMN>
    </SFA>
    <DEFECTCODE>26451</DEFECTCODE>
    <DESCRIPTION>Arithmetic overflow: Using operator '*' on a 4 byte value and then casting the result to a 8 byte value. Cast the value to the wider type before calling operator '*' to avoid overflow (io.2).</DESCRIPTION>
    <FUNCTION>stbi__hdr_load</FUNCTION>
    <DECORATED>?stbi__hdr_load@@YAPEAMPEAUstbi__context@@PEAH11HPEAUstbi__result_info@@@Z</DECORATED>
    <FUNCLINE>7081</FUNCLINE>
    <PATH></PATH>
  </DEFECT>
  <DEFECT>
    <SFA>
      <FILEPATH>G:\Compute Shader\framework\ext\</FILEPATH>
      <FILENAME>stb_image.h</FILENAME>
      <LINE>7146</LINE>
      <COLUMN>43</COLUMN>
    </SFA>
    <DEFECTCODE>26451</DEFECTCODE>
    <DESCRIPTION>Arithmetic overflow: Using operator '*' on a 4 byte value and then casting the result to a 8 byte value. Cast the value to the wider type before calling operator '*' to avoid overflow (io.2).</DESCRIPTION>
    <FUNCTION>stbi__hdr_load</FUNCTION>
    <DECORATED>?stbi__hdr_load@@YAPEAMPEAUstbi__context@@PEAH11HPEAUstbi__result_info@@@Z</DECORATED>
    <FUNCLINE>7081</FUNCLINE>
    <PATH></PATH>
  </DEFECT>
  <DEFECT>
    <SFA>
      <FILEPATH>G:\Compute Shader\framework\ext\</FILEPATH>
      <FILENAME>stb_image.h</FILENAME>
      <LINE>7146</LINE>
      <COLUMN>66</COLUMN>
    </SFA>
    <DEFECTCODE>26451</DEFECTCODE>
    <DESCRIPTION>Arithmetic overflow: Using operator '*' on a 4 byte value and then casting the result to a 8 byte value. Cast the value to the wider type before calling operator '*' to avoid overflow (io.2).</DESCRIPTION>
    <FUNCTION>stbi__hdr_load</FUNCTION>
    <DECORATED>?stbi__hdr_load@@YAPEAMPEAUstbi__context@@PEAH11HPEAUstbi__result_info@@@Z</DECORATED>
    <FUNCLINE>7081</FUNCLINE>
    <PATH></PATH>
  </DEFECT>
  <DEFECT>
    <SFA>
      <FILEPATH>G:\Compute Shader\framework\ext\</FILEPATH>
      <FILENAME>stb_image.h</FILENAME>
      <LINE>7203</LINE>
      <COLUMN>52</COLUMN>
    </SFA>
    <DEFECTCODE>26451</DEFECTCODE>
    <DESCRIPTION>Arithmetic overflow: Using operator '*' on a 4 byte value and then casting the result to a 8 byte value. Cast the value to the wider type before calling operator '*' to avoid overflow (io.2).</DESCRIPTION>
    <FUNCTION>stbi__hdr_load</FUNCTION>
    <DECORATED>?stbi__hdr_load@@YAPEAMPEAUstbi__context@@PEAH11HPEAUstbi__result_info@@@Z</DECORATED>
    <FUNCLINE>7081</FUNCLINE>
    <PATH></PATH>
  </DEFECT>
  <DEFECT>
    <SFA>
      <FILEPATH>G:\Compute Shader\framework\ext\</FILEPATH>
      <FILENAME>stb_image.h</FILENAME>
      <LINE>7203</LINE>
      <COLUMN>48</COLUMN>
    </SFA>
    <DEFECTCODE>26451</DEFECTCODE>
    <DESCRIPTION>Arithmetic overflow: Using operator '+' on a 4 byte value and then casting the result to a 8 byte value. Cast the value to the wider type before calling operator '+' to avoid overflow (io.2).</DESCRIPTION>
    <FUNCTION>stbi__hdr_load</FUNCTION>
    <DECORATED>?stbi__hdr_load@@YAPEAMPEAUstbi__context@@PEAH11HPEAUstbi__result_info@@@Z</DECORATED>
    <FUNCLINE>7081</FUNCLINE>
    <PATH></PATH>
  </DEFECT>
  <DEFECT>
    <SFA>
      <FILEPATH>G:\Compute Shader\framework\ext\</FILEPATH>
      <FILENAME>stb_image.h</FILENAME>
      <LINE>7203</LINE>
      <COLUMN>41</COLUMN>
    </SFA>
    <DEFECTCODE>26451</DEFECTCODE>
    <DESCRIPTION>Arithmetic overflow: Using operator '*' on a 4 byte value and then casting the result to a 8 byte value. Cast the value to the wider type before calling operator '*' to avoid overflow (io.2).</DESCRIPTION>
    <FUNCTION>stbi__hdr_load</FUNCTION>
    <DECORATED>?stbi__hdr_load@@YAPEAMPEAUstbi__context@@PEAH11HPEAUstbi__result_info@@@Z</DECORATED>
    <FUNCLINE>7081</FUNCLINE>
    <PATH></PATH>
  </DEFECT>
  <DEFECT>
    <SFA>
      <FILEPATH>G:\Compute Shader\framework\ext\</FILEPATH>
      <FILENAME>stb_image.h</FILENAME>
      <LINE>7203</LINE>
      <COLUMN>75</COLUMN>
    </SFA>
    <DEFECTCODE>26451</DEFECTCODE>
    <DESCRIPTION>Arithmetic overflow: Using operator '*' on a 4 byte value and then casting the result to a 8 byte value. Cast the value to the wider type before calling operator '*' to avoid overflow (io.2).</DESCRIPTION>
    <FUNCTION>stbi__hdr_load</FUNCTION>
    <DECORATED>?stbi__hdr_load@@YAPEAMPEAUstbi__context@@PEAH11HPEAUstbi__result_info@@@Z</DECORATED>
    <FUNCLINE>7081</FUNCLINE>
    <PATH></PATH>
  </DEFECT>
  <DEFECT>
    <SFA>
      <FILEPATH>G:\Compute Shader\framework\</FILEPATH>
      <FILENAME>imagedecode.cpp</FILENAME>
      <LINE>20</LINE>
      <COLUMN>30</COLUMN>
    </SFA>
    <DEFECTCODE>26451</DEFECTCODE>
    <DESCRIPTION>Arithmetic overflow: Using operator '*' on a 4 byte value and then casting the result to a 8 byte value. Cast the value to the wider type before calling operator '*' to avoid overflow (io.2).</DESCRIPTION>
    <FUNCTION>decodeIt</FUNCTION>
    <DECORATED>?decodeIt@@YA?AV?$tuple@HHV?$basic_string@DU?$char_traits@D@std@@V?$allocator@D@2@@std@@V?$vector@DV?$allocator@D@std@@@2@@std@@PEBDI@Z</DECORATED>
    <FUNCLINE>10</FUNCLINE>
    <PATH></PATH>
  </DEFECT>
  <DEFECT>
    <SFA>
      <FILEPATH>G:\Compute Shader\framework\</FILEPATH>
      <FILENAME>imagedecode.cpp</FILENAME>
      <LINE>20</LINE>
      <COLUMN>28</COLUMN>
    </SFA>
    <DEFECTCODE>26451</DEFECTCODE>
    <DESCRIPTION>Arithmetic overflow: Using operator '*' on a 4 byte value and then casting the result to a 8 byte value. Cast the value to the wider type before calling operator '*' to avoid overflow (io.2).</DESCRIPTION>
    <FUNCTION>decodeIt</FUNCTION>
    <DECORATED>?decodeIt@@YA?AV?$tuple@HHV?$basic_string@DU?$char_traits@D@std@@V?$allocator@D@2@@std@@V?$vector@DV?$allocator@D@std@@@2@@std@@PEBDI@Z</DECORATED>
    <FUNCLINE>10</FUNCLINE>
    <PATH></PATH>
  </DEFECT>
  <DEFECT>
    <SFA>
      <FILEPATH>G:\Compute Shader\framework\</FILEPATH>
      <FILENAME>imagedecode.cpp</FILENAME>
      <LINE>21</LINE>
      <COLUMN>48</COLUMN>
    </SFA>
    <DEFECTCODE>26451</DEFECTCODE>
    <DESCRIPTION>Arithmetic overflow: Using operator '*' on a 4 byte value and then casting the result to a 8 byte value. Cast the value to the wider type before calling operator '*' to avoid overflow (io.2).</DESCRIPTION>
    <FUNCTION>decodeIt</FUNCTION>
    <DECORATED>?decodeIt@@YA?AV?$tuple@HHV?$basic_string@DU?$char_traits@D@std@@V?$allocator@D@2@@std@@V?$vector@DV?$allocator@D@std@@@2@@std@@PEBDI@Z</DECORATED>
    <FUNCLINE>10</FUNCLINE>
    <PATH></PATH>
  </DEFECT>
  <DEFECT>
    <SFA>
      <FILEPATH>G:\Compute Shader\framework\</FILEPATH>
      <FILENAME>imagedecode.cpp</FILENAME>
      <LINE>21</LINE>
      <COLUMN>46</COLUMN>
    </SFA>
    <DEFECTCODE>26451</DEFECTCODE>
    <DESCRIPTION>Arithmetic overflow: Using operator '*' on a 4 byte value and then casting the result to a 8 byte value. Cast the value to the wider type before calling operator '*' to avoid overflow (io.2).</DESCRIPTION>
    <FUNCTION>decodeIt</FUNCTION>
    <DECORATED>?decodeIt@@YA?AV?$tuple@HHV?$basic_string@DU?$char_traits@D@std@@V?$allocator@D@2@@std@@V?$vector@DV?$allocator@D@std@@@2@@std@@PEBDI@Z</DECORATED>
    <FUNCLINE>10</FUNCLINE>
    <PATH></PATH>
  </DEFECT>
  <DEFECT>
    <SFA>
      <FILEPATH>G:\Compute Shader\framework\</FILEPATH>
      <FILENAME>imagedecode.cpp</FILENAME>
      <LINE>44</LINE>
      <COLUMN>30</COLUMN>
    </SFA>
    <DEFECTCODE>26451</DEFECTCODE>
    <DESCRIPTION>Arithmetic overflow: Using operator '*' on a 4 byte value and then casting the result to a 8 byte value. Cast the value to the wider type before calling operator '*' to avoid overflow (io.2).</DESCRIPTION>
    <FUNCTION>imagedecode::decode16</FUNCTION>
    <DECORATED>?decode16@imagedecode@@YA?AV?$tuple@HHV?$basic_string@DU?$char_traits@D@std@@V?$allocator@D@2@@std@@V?$vector@GV?$allocator@G@std@@@2@@std@@AEBV?$vector@DV?$allocator@D@std@@@3@@Z</DECORATED>
    <FUNCLINE>35</FUNCLINE>
    <PATH></PATH>
  </DEFECT>
  <DEFECT>
    <SFA>
      <FILEPATH>G:\Compute Shader\framework\</FILEPATH>
      <FILENAME>imagedecode.cpp</FILENAME>
      <LINE>44</LINE>
      <COLUMN>28</COLUMN>
    </SFA>
    <DEFECTCODE>26451</DEFECTCODE>
    <DESCRIPTION>Arithmetic overflow: Using operator '*' on a 4 byte value and then casting the result to a 8 byte value. Cast the value to the wider type before calling operator '*' to avoid overflow (io.2).</DESCRIPTION>
    <FUNCTION>imagedecode::decode16</FUNCTION>
    <DECORATED>?decode16@imagedecode@@YA?AV?$tuple@HHV?$basic_string@DU?$char_traits@D@std@@V?$allocator@D@2@@std@@V?$vector@GV?$allocator@G@std@@@2@@std@@AEBV?$vector@DV?$allocator@D@std@@@3@@Z</DECORATED>
    <FUNCLINE>35</FUNCLINE>
    <PATH></PATH>
  </DEFECT>
  <DEFECT>
    <SFA>
      <FILEPATH>G:\Compute Shader\framework\</FILEPATH>
      <FILENAME>imagedecode.cpp</FILENAME>
      <LINE>45</LINE>
      <COLUMN>48</COLUMN>
    </SFA>
    <DEFECTCODE>26451</DEFECTCODE>
    <DESCRIPTION>Arithmetic overflow: Using operator '*' on a 4 byte value and then casting the result to a 8 byte value. Cast the value to the wider type before calling operator '*' to avoid overflow (io.2).</DESCRIPTION>
    <FUNCTION>imagedecode::decode16</FUNCTION>
    <DECORATED>?decode16@imagedecode@@YA?AV?$tuple@HHV?$basic_string@DU?$char_traits@D@std@@V?$allocator@D@2@@std@@V?$vector@GV?$allocator@G@std@@@2@@std@@AEBV?$vector@DV?$allocator@D@std@@@3@@Z</DECORATED>
    <FUNCLINE>35</FUNCLINE>
    <PATH></PATH>
  </DEFECT>
  <DEFECT>
    <SFA>
      <FILEPATH>G:\Compute Shader\framework\</FILEPATH>
      <FILENAME>imagedecode.cpp</FILENAME>
      <LINE>45</LINE>
      <COLUMN>46</COLUMN>
    </SFA>
    <DEFECTCODE>26451</DEFECTCODE>
    <DESCRIPTION>Arithmetic overflow: Using operator '*' on a 4 byte value and then casting the result to a 8 byte value. Cast the value to the wider type before calling operator '*' to avoid overflow (io.2).</DESCRIPTION>
    <FUNCTION>imagedecode::decode16</FUNCTION>
    <DECORATED>?decode16@imagedecode@@YA?AV?$tuple@HHV?$basic_string@DU?$char_traits@D@std@@V?$allocator@D@2@@std@@V?$vector@GV?$allocator@G@std@@@2@@std@@AEBV?$vector@DV?$allocator@D@std@@@3@@Z</DECORATED>
    <FUNCLINE>35</FUNCLINE>
    <PATH></PATH>
  </DEFECT>
</DEFECTS>